mapsbr/__init__.py
mapsbr/arcgis.py
mapsbr/ibgemaps.py
mapsbr/helpers/__init__.py
mapsbr/helpers/ibgetools.py
mapsbr/helpers/request.py
mapsbr/helpers/utils.py
mapsbr-0.0.4.dist-info/LICENSE
mapsbr-0.0.4.dist-info/METADATA
mapsbr-0.0.4.dist-info/WHEEL
mapsbr-0.0.4.dist-info/top_level.txt
mapsbr-0.0.4.dist-info/RECORD
